{"k":"lobby:room:167819","v":"{\"code\": \"167819\", \"game\": \"stackrace\", \"phase\": \"playing\", \"created\": 1784289098.060506, \"turn\": null, \"winner\": null, \"winners\": null, \"loser\": null, \"result\": null, \"message\": \"Падайте и набирайте очки! Кто больше — тот победил.\", \"vs_ai\": true, \"vs_local\": false, \"max_players\": 2, \"ai_slot\": \"p2\", \"players\": {\"p1\": {\"token\": \"0b32d44632f3f34499dda10ea32ec21e\", \"name\": \"A\", \"ai\": false}, \"p2\": {\"token\": \"e98baf2e466494098ef86d838463495b\", \"name\": \"Компьютер\", \"ai\": true}}, \"rematch_votes\": {}, \"state\": {\"phase\": \"playing\", \"players\": {\"p1\": {\"board\": [[0, 0, 0, 0, 0, 0, 0, 0, 0, 0], [0, 0, 0, 0, 0, 0, 0, 0, 0, 0], [0, 0, 0, 0, 0, 0, 0, 0, 0, 0], [0, 0, 0, 0, 0, 0, 0, 0, 0, 0], [0, 0, 0, 0, 0, 0, 0, 0, 0, 0], [0, 0, 0, 0, 0, 0, 0, 0, 0, 0], [0, 0, 0, 0, 0, 0, 0, 0, 0, 0], [0, 0, 0, 0, 0, 0, 0, 0, 0, 0], [0, 0, 0, 0, 0, 0, 0, 0, 0, 0], [0, 0, 0, 0, 0, 0, 0, 0, 0, 0], [0, 0, 0, 0, 0, 0, 0, 0, 0, 0], [0, 0, 0, 0, 0, 0, 0, 0, 0, 0], [0, 0, 0, 0, 0, 0, 0, 0, 0, 0], [0, 0, 0, 0, 0, 0, 0, 0, 0, 0], [0, 0, 0, 0, 0, 0, 0, 0, 0, 0], [0, 0, 0, 0, 0, 0, 0, 0, 0, 0], [0, 0, 0, 0, 0, 0, 0, 0, 0, 0], [0, 0, 0, 0, 5, 0, 0, 0, 0, 0], [0, 0, 0, 5, 5, 0, 0, 0, 0, 0], [0, 0, 0, 5, 0, 0, 0, 0, 0, 0]], \"piece\": {\"type\": \"J\", \"x\": 4, \"y\": 0, \"rot\": 0}, \"queue\": [\"T\", \"S\", \"I\", \"L\", \"O\"], \"bag\": [], \"score\": 35, \"lines\": 0, \"level\": 1, \"alive\": true, \"drop_at\": 1784289098.9331026}, \"p2\": {\"board\": [[0, 0, 0, 0, 0, 0, 0, 0, 0, 0], [0, 0, 0, 0, 0, 0, 0, 0, 0, 0], [0, 0, 0, 0, 0, 0, 0, 0, 0, 0], [0, 0, 0, 0, 0, 0, 0, 0, 0, 0], [0, 0, 0, 0, 0, 0, 0, 0, 0, 0], [0, 0, 0, 0, 0, 0, 0, 0, 0, 0], [0, 0, 0, 0, 0, 0, 0, 0, 0, 0], [0, 0, 0, 0, 0, 0, 0, 0, 0, 0], [0, 0, 0, 0, 0, 0, 0, 0, 0, 0], [0, 0, 0, 0, 0, 0, 0, 0, 0, 0], [0, 0, 0, 0, 0, 0, 0, 0, 0, 0], [0, 0, 0, 0, 0, 0, 0, 0, 0, 0], [0, 0, 0, 0, 0, 0, 0, 0, 0, 0], [0, 0, 0, 0, 0, 0, 0, 0, 0, 0], [0, 0, 0, 0, 0, 0, 0, 0, 0, 0], [0, 0, 0, 0, 0, 0, 0, 0, 0, 0], [0, 0, 0, 0, 0, 0, 0, 0, 0, 0], [0, 0, 0, 0, 0, 0, 0, 0, 0, 0], [0, 0, 0, 0, 0, 0, 0, 0, 0, 0], [0, 0, 0, 0, 0, 0, 0, 0, 0, 0]], \"piece\": {\"type\": \"L\", \"x\": 4, \"y\": 0, \"rot\": 0}, \"queue\": [\"J\", \"S\", \"Z\", \"T\", \"O\"], \"bag\": [\"I\"], \"score\": 0, \"lines\": 0, \"level\": 1, \"alive\": true, \"drop_at\": 1784289098.9105809}}, \"seed\": \"385ad788\"}, \"ai_due\": 1784289098.3331091}","exp":1784299898.0858552}